Workbook
Name IQ_CH: 110000
Name IQ_CQ: 5000
Name IQ_CY: 10000
Name IQ_DAILY: 500000
Name IQ_FH: 100000
Name IQ_FQ: 500
Name IQ_FY: 1000
Name IQ_LTM: 2000
Name IQ_MONTH: 15000
Name IQ_NTM: 6000
Name IQ_WEEK: 50000
Name IQ_YTD: 3000

Sheet Financials
B2: Company name
B3: All amounts in Millions except per share data (inputs in blue)
B5: =$B$2& " Valuation Summary" -> Company name Valuation Summary
B7: Fiscal Year | D7: 2016 | E7: =D7+1 -> 2017 | F7: =E7+1 -> 2018 | G7: =F7+1 -> 2019 | H7: =G7+1 -> 2020 | I7: =H7+1 -> 2021 | J7: =I7+1 -> 2022 | K7: =J7+1 -> 2023 | L7: =K7+1 -> 2024 | M7: =L7+1 -> 2025
B8: Company symbol
B9: Share price date
B10: Share Price:
B11: Shares Outstanding
B12: Market Cap | D12: =+D10*D11 -> 0 | E12: =+E10*E11 -> 0 | F12: =+F10*F11 -> 0 | G12: =+G10*G11 -> 0 | H12: =+H11*H10 -> 0 | I12: =+I11*I10 -> 0 | J12: =+J11*J10 -> 0 | K12: =+K11*K10 -> 0 | L12: =+L11*L10 -> 0 | M12: =+M11*M10 -> 0
B13: Less: Cash + securities | D13: =D53+D59 | E13: =E53+E59 | F13: =F53+F59 | G13: =G53+G59 | H13: =H53+H59 | I13: =I53+I59 | J13: =J53+J59 | K13: =K53+K59 | ... M13: =M53+M59
B14: Plus: Debt | D14: =D64 -> 0 | E14: =E64 -> 0 | F14: =F64 -> 0 | G14: =G64 -> 0 | H14: =H64 -> 0 | I14: =I64 -> 0 | J14: =J64 -> 0 | K14: =K64 -> 0 | ... M14: =M64 -> 0
B15: Enterprise Value | D15: =D12-D13+D14 -> 0 | E15: =E12-E13+E14 -> 0 | F15: =F12-F13+F14 -> 0 | G15: =G12-G13+G14 -> 0 | H15: =H12-H13+H14 -> 0 | I15: =I12-I13+I14 -> 0 | J15: =J12-J13+J14 -> 0 | K15: =K12-K13+K14 -> 0 | ... M15: =M12-M13+M14 -> 0
B16: EV/share | D16: =+D15/D11 -> #DIV/0! | E16: =+E15/E11 -> #DIV/0! | F16: =+F15/F11 -> #DIV/0! | G16: =+G15/G11 -> #DIV/0! | H16: =+H15/H11 -> #DIV/0! | I16: =+I15/I11 -> #DIV/0! | J16: =+J15/J11 -> #DIV/0! | K16: =+K15/K11 -> #DIV/0! | ... M16: =+M15/M11 -> #DIV/0!
B17: Book Value (Equity) | D17: =D68 -> 0 | E17: =E68 -> 0 | F17: =F68 -> 0 | G17: =G68 -> 0 | H17: =H68 -> 0 | I17: =I68 -> 0 | J17: =J68 -> 0 | K17: =K68 -> 0 | ... M17: =M68 -> 0
B20: ="Summary Values - " & M7 & " (per share basis)" -> Summary Values - 2025 (per share basis)
B21: Invested Capital | D21: =M138/M11 -> #DIV/0! | E21: =+D21/$D$25 -> #DIV/0!
B22: PV of Comp Advantage | D22: =M139/M11 -> #DIV/0! | E22: =+D22/$D$25 -> #DIV/0!
B23: Earnings Power Value | D23: =M140/M11 -> #DIV/0! | E23: =+D23/$D$25 -> #DIV/0!
B24: Market implied value of growth | D24: =M142/M11 -> #DIV/0! | E24: =+D24/$D$25 -> #DIV/0!
B25: EV/Share | D25: =+D23+D24 -> #DIV/0!
B28: =$B$2& " Historical Financials" -> Company name Historical Financials
B29: Income Statement
D30: =D7 -> 2016 | E30: =D30+1 -> 2017 | F30: =E30+1 -> 2018 | G30: =F30+1 -> 2019 | H30: =G30+1 -> 2020 | I30: =H30+1 -> 2021 | J30: =I30+1 -> 2022 | K30: =+K7 -> 2023 | L30: =+L7 -> 2024 | M30: =+M7 -> 2025
B31: Revenue
B32: COGS
B33: Gross Profit | D33: =SUM(D31:D32) -> 0 | E33: =SUM(E31:E32) -> 0 | F33: =SUM(F31:F32) -> 0 | G33: =SUM(G31:G32) -> 0 | H33: =SUM(H31:H32) -> 0 | I33: =SUM(I31:I32) -> 0 | J33: =SUM(J31:J32) -> 0 | K33: =SUM(K31:K32) -> 0 | ... M33: =SUM(M31:M32) -> 0
C34: GPM | D34: =D33/D31 -> #DIV/0! | E34: =E33/E31 -> #DIV/0! | F34: =F33/F31 -> #DIV/0! | G34: =G33/G31 -> #DIV/0! | H34: =H33/H31 -> #DIV/0! | I34: =I33/I31 -> #DIV/0! | J34: =J33/J31 -> #DIV/0! | K34: =K33/K31 -> #DIV/0! | ... M34: =M33/M31 -> #DIV/0!
B36: Operating Expenses (SG&A)
B38: Operating Profit | D38: =+D33-(D36+D37) -> 0 | E38: =+E33-(E36+E37) -> 0 | F38: =+F33-(F36+F37) -> 0 | G38: =+G33-(G36+G37) -> 0 | H38: =+H33-(H36+H37) -> 0 | I38: =+I33-(I36+I37) -> 0 | J38: =+J33-(J36+J37) -> 0 | K38: =+K33-(K36+K37) -> 0 | ... M38: =+M33-(M36+M37) -> 0
C39: OPM | D39: =D38/D31 -> #DIV/0! | E39: =E38/E31 -> #DIV/0! | F39: =F38/F31 -> #DIV/0! | G39: =G38/G31 -> #DIV/0! | H39: =H38/H31 -> #DIV/0! | I39: =I38/I31 -> #DIV/0! | J39: =J38/J31 -> #DIV/0! | K39: =K38/K31 -> #DIV/0! | ... M39: =M38/M31 -> #DIV/0!
B41: Interest and other income
B42: Income Before Taxes | D42: =+D38+D41 -> 0 | E42: =+E38+E41 -> 0 | F42: =+F38+F41 -> 0 | G42: =+G38+G41 -> 0 | H42: =+H38+H41 -> 0 | I42: =+I38+I41 -> 0 | J42: =+J38+J41 -> 0 | K42: =+K38+K41 -> 0 | ... M42: =+M38+M41 -> 0
B44: Taxes
C45: Rate | D45: =D44/D42 -> #DIV/0! | E45: =E44/E42 -> #DIV/0! | F45: =F44/F42 -> #DIV/0! | G45: =G44/G42 -> #DIV/0! | H45: =H44/H42 -> #DIV/0! | I45: =I44/I42 -> #DIV/0! | J45: =J44/J42 -> #DIV/0! | K45: =K44/K42 -> #DIV/0! | ... M45: =M44/M42 -> #DIV/0!
B46: Minority Interest in Earnings
B48: Net Income | D48: =+D42-D44+D46 -> 0 | E48: =+E42-E44+E46 -> 0 | F48: =+F42-F44+F46 -> 0 | G48: =+G42-G44+G46 -> 0 | H48: =+H42-H44+H46 -> 0 | I48: =+I42-I44+I46 -> 0 | J48: =+J42-J44+J46 -> 0 | K48: =+K42-K44+K46 -> 0 | ... M48: =+M42-M44+M46 -> 0
C49: Margin | D49: =D48/D31 -> #DIV/0! | E49: =E48/E31 -> #DIV/0! | F49: =F48/F31 -> #DIV/0! | G49: =G48/G31 -> #DIV/0! | H49: =H48/H31 -> #DIV/0! | I49: =I48/I31 -> #DIV/0! | J49: =J48/J31 -> #DIV/0! | K49: =K48/K31 -> #DIV/0! | ... M49: =M48/M31 -> #DIV/0!
B51: Balance Sheet
D52: =D7 -> 2016 | E52: =D52+1 -> 2017 | F52: =E52+1 -> 2018 | G52: =F52+1 -> 2019 | H52: =G52+1 -> 2020 | I52: =H52+1 -> 2021 | J52: =I52+1 -> 2022 | K52: =+K7 -> 2023 | L52: =+L7 -> 2024 | M52: =+M7 -> 2025
B53: Cash, Equivalents + Current Securities
B54: Inventories
B55: A/R
B56: Total Current Assets
B57: PP&E + Operating Lease
B58: Total Assets
B59: Non-current marketable securities
B60: A/P
B61: Other Current Liabilities | D61: =D62-D60 -> 0 | E61: =E62-E60 -> 0 | F61: =F62-F60 -> 0 | G61: =G62-G60 -> 0 | H61: =H62-H60 -> 0 | I61: =I62-I60 -> 0 | J61: =J62-J60 -> 0 | K61: =K62-K60 -> 0 | ... M61: =M62-M60 -> 0
B62: Total Current Liabilities
B63: of which: current debt + current op. lease
B64: Total Debt + Operating Leases
B65: Total Liabilities
B67: Net Debt | D67: =D64-D53 -> 0 | E67: =E64-E53 -> 0 | F67: =F64-F53 -> 0 | G67: =G64-G53 -> 0 | H67: =H64-H53 -> 0 | I67: =I64-I53 -> 0 | J67: =J64-J53 -> 0 | K67: =K64-K53 -> 0 | ... M67: =M64-M53 -> 0
B68: Book Value | D68: =D58-D65 -> 0 | E68: =E58-E65 -> 0 | F68: =F58-F65 -> 0 | G68: =G58-G65 -> 0 | H68: =H58-H65 -> 0 | I68: =I58-I65 -> 0 | J68: =J58-J65 -> 0 | K68: =K58-K65 -> 0 | ... M68: =M58-M65 -> 0
B69: Intangible Assets &/or GW
B70: *Tangible Book Value | D70: =+D68-D69 -> 0 | E70: =+E68-E69 -> 0 | F70: =+F68-F69 -> 0 | G70: =+G68-G69 -> 0 | H70: =+H68-H69 -> 0 | I70: =+I68-I69 -> 0 | J70: =+J68-J69 -> 0 | K70: =+K68-K69 -> 0 | ... M70: =+M68-M69 -> 0
B72: =$B$2& " NOPAT" -> Company name NOPAT
B75: EBITDA Build-up | D75: =D7 -> 2016 | E75: =D75+1 -> 2017 | F75: =E75+1 -> 2018 | G75: =F75+1 -> 2019 | H75: =G75+1 -> 2020 | I75: =H75+1 -> 2021 | J75: =I75+1 -> 2022 | K75: =+K7 -> 2023 | L75: =+L7 -> 2024 | M75: =+M7 -> 2025
B76: Net Income | D76: =D48 -> 0 | E76: =E48 -> 0 | F76: =F48 -> 0 | G76: =G48 -> 0 | H76: =H48 -> 0 | I76: =I48 -> 0 | J76: =J48 -> 0 | K76: =K48 -> 0 | ... M76: =M48 -> 0
B77: Taxes | D77: =+D44 -> 0 | E77: =+E44 -> 0 | F77: =+F44 -> 0 | G77: =+G44 -> 0 | H77: =+H44 -> 0 | I77: =+I44 -> 0 | J77: =+J44 -> 0 | K77: =+K44 -> 0 | ... M77: =+M44 -> 0
B78: Less: Interest and other income | D78: =-D41 | E78: =-E41 | F78: =-F41 | G78: =-G41 | H78: =-H41 | I78: =-I41 | J78: =-J41 | K78: =-K41 | ... M78: =-M41
B79: D&A
B80: EBITDA | D80: =SUM(D76:D79) -> 0 | E80: =SUM(E76:E79) -> 0 | F80: =SUM(F76:F79) -> 0 | G80: =SUM(G76:G79) -> 0 | H80: =SUM(H76:H79) -> 0 | I80: =SUM(I76:I79) -> 0 | J80: =SUM(J76:J79) -> 0 | K80: =SUM(K76:K79) -> 0 | ... M80: =SUM(M76:M79) -> 0
B81: Margin | D81: =D80/D31 -> #DIV/0! | E81: =E80/E31 -> #DIV/0! | F81: =F80/F31 -> #DIV/0! | G81: =G80/G31 -> #DIV/0! | H81: =H80/H31 -> #DIV/0! | I81: =I80/I31 -> #DIV/0! | J81: =J80/J31 -> #DIV/0! | K81: =K80/K31 -> #DIV/0! | ... M81: =M80/M31 -> #DIV/0!
B83: Non-operating / One Time Items | D83: 0 | E83: 0 | F83: 0 | G83: 0 | H83: 0 | I83: 0 | J83: 0
B84: EBITDA (adjusted) | D84: =D80+D83 -> 0 | E84: =E80+E83 -> 0 | F84: =F80+F83 -> 0 | G84: =G80+G83 -> 0 | H84: =H80+H83 -> 0 | I84: =I80+I83 -> 0 | J84: =J80+J83 -> 0 | K84: =K80+K83 -> 0 | ... M84: =M80+M83 -> 0
B85: Margin (adjusted) | D85: =D84/D31 -> #DIV/0! | E85: =E84/E31 -> #DIV/0! | F85: =F84/F31 -> #DIV/0! | G85: =G84/G31 -> #DIV/0! | H85: =H84/H31 -> #DIV/0! | I85: =I84/I31 -> #DIV/0! | J85: =J84/J31 -> #DIV/0! | K85: =K84/K31 -> #DIV/0! | ... M85: =M84/M31 -> #DIV/0!
B87: Free Cash Flow Maintenance
B88: Operating Profit | D88: =+D38 -> 0 | E88: =+E38 -> 0 | F88: =+F38 -> 0 | G88: =+G38 -> 0 | H88: =+H38 -> 0 | I88: =+I38 -> 0 | J88: =+J38 -> 0 | K88: =+K38 -> 0 | ... M88: =+M38 -> 0
B89: Taxes | D89: =+D77 -> 0 | E89: =+E77 -> 0 | F89: =+F77 -> 0 | G89: =+G77 -> 0 | H89: =+H77 -> 0 | I89: =+I77 -> 0 | J89: =+J77 -> 0 | K89: =+K77 -> 0 | ... M89: =+M77 -> 0
B90: Operating Profit After Tax | D90: =+D88-D89 -> 0 | E90: =+E88-E89 -> 0 | F90: =+F88-F89 -> 0 | G90: =+G88-G89 -> 0 | H90: =+H88-H89 -> 0 | I90: =+I88-I89 -> 0 | J90: =+J88-J89 -> 0 | K90: =+K88-K89 -> 0 | ... M90: =+M88-M89 -> 0
B91: Plus: D&A | D91: =D79 -> 0 | E91: =E79 -> 0 | F91: =F79 -> 0 | G91: =G79 -> 0 | H91: =H79 -> 0 | I91: =I79 -> 0 | J91: =J79 -> 0 | K91: =K79 -> 0 | ... M91: =M79 -> 0
B92: Less: Capex Maint | D92: =-D105 -> 0 | E92: =-E105 -> 0 | F92: =-F105 -> 0 | G92: =-G105 -> 0 | H92: =-H105 -> 0 | I92: =-I105 -> 0 | J92: =-J105 -> 0 | K92: =-K105 -> 0 | ... M92: =-M105 -> 0
B93: NOPAT | D93: =SUM(D90:D92) -> 0 | E93: =SUM(E90:E92) -> 0 | F93: =SUM(F90:F92) -> 0 | G93: =SUM(G90:G92) -> 0 | H93: =SUM(H90:H92) -> 0 | I93: =SUM(I90:I92) -> 0 | J93: =SUM(J90:J92) -> 0 | K93: =SUM(K90:K92) -> 0 | ... M93: =SUM(M90:M92) -> 0
B94: Margin | D94: =+D93/D31 -> #DIV/0! | E94: =+E93/E31 -> #DIV/0! | F94: =+F93/F31 -> #DIV/0! | G94: =+G93/G31 -> #DIV/0! | H94: =+H93/H31 -> #DIV/0! | I94: =+I93/I31 -> #DIV/0! | J94: =+J93/J31 -> #DIV/0! | K94: =+K93/K31 -> #DIV/0! | ... M94: =+M93/M31 -> #DIV/0!
B96: NOPAT | C96: =M93 -> 0
B97: WACC | C97: 0.1
B98: EPV | C98: =C96/C97 -> 0
B99: Shares Outstanding | C99: =M11 -> 0
B100: Per Share | C100: =C98/C99 -> #DIV/0!
B102: =$B$2& " Invested Capital Detail" -> Company name Invested Capital Detail
D104: =D7 -> 2016 | E104: =D104+1 -> 2017 | F104: =E104+1 -> 2018 | G104: =F104+1 -> 2019 | H104: =G104+1 -> 2020 | I104: =H104+1 -> 2021 | J104: =I104+1 -> 2022 | K104: =+K7 -> 2023 | L104: =+L7 -> 2024 | M104: =+M7 -> 2025
B105: Depreciation | D105: =D79 -> 0 | E105: =E79 -> 0 | F105: =F79 -> 0 | G105: =G79 -> 0 | H105: =H79 -> 0 | I105: =I79 -> 0 | J105: =J79 -> 0 | K105: =K79 -> 0 | ... M105: =M79 -> 0
B106: CapEx
B107: Maintenance CapEx | D107: =+D105 -> 0 | E107: =+E105 -> 0 | F107: =+F105 -> 0 | G107: =+G105 -> 0 | H107: =+H105 -> 0 | I107: =+I105 -> 0 | J107: =+J105 -> 0 | K107: =+K105 -> 0 | ... M107: =+M105 -> 0
B108: Growth CapEx | D108: =+D106-D107 -> 0 | E108: =+E106-E107 -> 0 | F108: =+F106-F107 -> 0 | G108: =+G106-G107 -> 0 | H108: =+H106-H107 -> 0 | I108: =+I106-I107 -> 0 | J108: =+J106-J107 -> 0 | K108: =+K106-K107 -> 0 | ... M108: =+M106-M107 -> 0
B110: Total PP&E
B111: Less: accumulated depreciation
B112: PP&E | D112: =+D110-D111 -> 0 | E112: =+E110-E111 -> 0 | F112: =+F110-F111 -> 0 | G112: =+G110-G111 -> 0 | H112: =+H110-H111 -> 0 | I112: =+I110-I111 -> 0 | J112: =J57 -> 0 | K112: =K57 -> 0 | L112: =L57 -> 0 | M112: =M57 -> 0
B114: =$B$2& " ROIC Analysis" -> Company name ROIC Analysis
D116: =D7 -> 2016 | E116: =D116+1 -> 2017 | F116: =E116+1 -> 2018 | G116: =F116+1 -> 2019 | H116: =G116+1 -> 2020 | I116: =H116+1 -> 2021 | J116: =I116+1 -> 2022 | K116: =+K7 -> 2023 | L116: =+L7 -> 2024 | M116: =+M7 -> 2025 | O116: ROIC Equations
B117: EBITDA (adjusted) | D117: =D84 -> 0 | E117: =E84 -> 0 | F117: =F84 -> 0 | G117: =G84 -> 0 | H117: =H84 -> 0 | I117: =I84 -> 0 | J117: =J84 -> 0 | K117: =K84 -> 0 | ... M117: =M84 -> 0
B118: Maint. Capex | D118: =D92 -> 0 | E118: =E92 -> 0 | F118: =F92 -> 0 | G118: =G92 -> 0 | H118: =H92 -> 0 | I118: =I92 -> 0 | J118: =J92 -> 0 | K118: =K92 -> 0 | ... M118: =M92 -> 0 | O118: NOPAT
O119: Invested Capital
B120: Pre-tax | D120: =+D117+D118 -> 0 | E120: =+E117+E118 -> 0 | F120: =+F117+F118 -> 0 | G120: =+G117+G118 -> 0 | H120: =+H117+H118 -> 0 | I120: =+I117+I118 -> 0 | J120: =+J117+J118 -> 0 | K120: =+K117+K118 -> 0 | ... M120: =+M117+M118 -> 0
B121: tax rate | D121: =+D45 -> #DIV/0! | E121: =+E45 -> #DIV/0! | F121: =+F45 -> #DIV/0! | G121: =+G45 -> #DIV/0! | H121: =+H45 -> #DIV/0! | I121: =+I45 -> #DIV/0! | J121: =+J45 -> #DIV/0! | K121: =+K45 -> #DIV/0! | ... M121: =+M45 -> #DIV/0! | O121: Which is equal to:
B122: taxes | D122: =+D120*D121 -> #DIV/0! | E122: =+E120*E121 -> #DIV/0! | F122: =+F120*F121 -> #DIV/0! | G122: =+G120*G121 -> #DIV/0! | H122: =+H120*H121 -> #DIV/0! | I122: =+I120*I121 -> #DIV/0! | J122: =+J120*J121 -> #DIV/0! | K122: =+K120*K121 -> #DIV/0! | ... M122: =+M120*M121 -> #DIV/0!
B123: NOPAT (implied) | D123: =+D120-D122 -> #DIV/0! | E123: =+E120-E122 -> #DIV/0! | F123: =+F120-F122 -> #DIV/0! | G123: =+G120-G122 -> #DIV/0! | H123: =+H120-H122 -> #DIV/0! | I123: =+I120-I122 -> #DIV/0! | J123: =+J120-J122 -> #DIV/0! | K123: =+K120-K122 -> #DIV/0! | ... M123: =+M120-M122 -> #DIV/0! | O123: (EBITDA - Maintence Capex - Taxes)
B124: % margin | D124: =+D123/D31 -> #DIV/0! | E124: =+E123/E31 -> #DIV/0! | F124: =+F123/F31 -> #DIV/0! | G124: =+G123/G31 -> #DIV/0! | H124: =+H123/H31 -> #DIV/0! | I124: =+I123/I31 -> #DIV/0! | J124: =+J123/J31 -> #DIV/0! | K124: =+K123/K31 -> #DIV/0! | ... M124: =+M123/M31 -> #DIV/0! | O124: PP&E + Net Working Capital
B126: PP&E | D126: =D112 -> 0 | E126: =E112 -> 0 | F126: =F112 -> 0 | G126: =G112 -> 0 | H126: =H112 -> 0 | I126: =I112 -> 0 | J126: =J112 -> 0 | K126: =K112 -> 0 | ... M126: =M112 -> 0
...

Sheet Charts
C2: =Financials!D7 -> 2016 | D2: =Financials!E7 -> 2017 | E2: =Financials!F7 -> 2018 | F2: =Financials!G7 -> 2019 | G2: =Financials!H7 -> 2020 | H2: =Financials!I7 -> 2021 | I2: =Financials!J7 -> 2022 | J2: =Financials!K7 -> 2023 | ... L2: =Financials!M7 -> 2025 | O2: Chart Names
O3: Top Left | Q3: =Financials!B2 & " "& "("&Financials!B8& ") - Enterprise Value (EV)" -> Company name (Company symbol) - Enterprise Value (EV)
B4: Invested capital | C4: =Financials!D138 -> 0 | D4: =Financials!E138 -> 0 | E4: =Financials!F138 -> 0 | F4: =Financials!G138 -> 0 | G4: =Financials!H138 -> 0 | H4: =Financials!I138 -> 0 | I4: =Financials!J138 -> 0 | J4: =Financials!K138 -> 0 | ... L4: =Financials!M138 -> 0 | O4: Top Middle | Q4: =Financials!B2 & " "& "("&Financials!B8& ") - Earnings Power Value (EPV)" -> Company name (Company symbol) - Earnings Power Value (EPV)
B5: Present value of competitive advantage | C5: =Financials!D139 -> #DIV/0! | D5: =Financials!E139 -> #DIV/0! | E5: =Financials!F139 -> #DIV/0! | F5: =Financials!G139 -> #DIV/0! | G5: =Financials!H139 -> #DIV/0! | H5: =Financials!I139 -> #DIV/0! | I5: =Financials!J139 -> #DIV/0! | J5: =Financials!K139 -> #DIV/0! | ... L5: =Financials!M139 -> #DIV/0! | O5: Top Right | Q5: =Financials!B2 & " "& "("&Financials!B8& ") - Earnings Power Value (EPV) (Percentage of EV)" -> Company name (Company symbol) - Earnings Power Value (EPV) (Percentage of EV)
B6: Earnings Power Value | C6: =Financials!D140 -> #DIV/0! | D6: =Financials!E140 -> #DIV/0! | E6: =Financials!F140 -> #DIV/0! | F6: =Financials!G140 -> #DIV/0! | G6: =Financials!H140 -> #DIV/0! | H6: =Financials!I140 -> #DIV/0! | I6: =Financials!J140 -> #DIV/0! | J6: =Financials!K140 -> #DIV/0! | ... L6: =Financials!M140 -> #DIV/0! | O6: Mid Left: | Q6: =Financials!B2 & " "& "("&Financials!B8& ") - Market-Implied Value of NOPAT Growth" -> Company name (Company symbol) - Market-Implied Value of NOPAT Growth
B7: Market Implied value of NOPAT growth | C7: =Financials!D142 -> #DIV/0! | D7: =Financials!E142 -> #DIV/0! | E7: =Financials!F142 -> #DIV/0! | F7: =Financials!G142 -> #DIV/0! | G7: =Financials!H142 -> #DIV/0! | H7: =Financials!I142 -> #DIV/0! | I7: =Financials!J142 -> #DIV/0! | J7: =Financials!K142 -> #DIV/0! | ... L7: =Financials!M142 -> #DIV/0! | O7: Mid Right: | Q7: =Financials!B2 & " "& "("&Financials!B8& ") - Historical Valuation in US Thousands" -> Company name (Company symbol) - Historical Valuation in US Thousands
B8: Enterprise Value (EV) | C8: =Financials!D143 -> 0 | D8: =Financials!E143 -> 0 | E8: =Financials!F143 -> 0 | F8: =Financials!G143 -> 0 | G8: =Financials!H143 -> 0 | H8: =Financials!I143 -> 0 | I8: =Financials!J143 -> 0 | J8: =Financials!K143 -> 0 | ... L8: =Financials!M143 -> 0 | O8: Bottom Left | Q8: =Financials!B2 & " "& "("&Financials!B8& ") - Market-Implied Value of NOPAT Growth" -> Company name (Company symbol) - Market-Implied Value of NOPAT Growth
O9: Bottom Right | Q9: =Financials!B2 & " "& "("&Financials!B8& ") - Market-Implied Value of NOPAT Growth (Percentage of EV)" -> Company name (Company symbol) - Market-Implied Value of NOPAT Growth (Percentage of EV)
B10: Market Implied value of NOPAT growth | C10: =C7/C8 -> #DIV/0! | D10: =D7/D8 -> #DIV/0! | E10: =E7/E8 -> #DIV/0! | F10: =F7/F8 -> #DIV/0! | G10: =G7/G8 -> #DIV/0! | H10: =H7/H8 -> #DIV/0! | I10: =I7/I8 -> #DIV/0! | J10: =J7/J8 -> #DIV/0! | ... L10: =L7/L8 -> #DIV/0!
B11: Earnings Power Value | C11: =C6/C8 -> #DIV/0! | D11: =D6/D8 -> #DIV/0! | E11: =E6/E8 -> #DIV/0! | F11: =F6/F8 -> #DIV/0! | G11: =G6/G8 -> #DIV/0! | H11: =H6/H8 -> #DIV/0! | I11: =I6/I8 -> #DIV/0! | J11: =J6/J8 -> #DIV/0! | ... L11: =L6/L8 -> #DIV/0!
C13: =+C2 -> 2016 | D13: =+D2 -> 2017 | E13: =+E2 -> 2018 | F13: =+F2 -> 2019 | G13: =+G2 -> 2020 | H13: =+H2 -> 2021 | I13: =+I2 -> 2022 | J13: =+J2 -> 2023 | ... L13: =+L2 -> 2025
B14: Revenue | C14: =+Financials!D31 -> 0 | D14: =+Financials!E31 -> 0 | E14: =+Financials!F31 -> 0 | F14: =+Financials!G31 -> 0 | G14: =+Financials!H31 -> 0 | H14: =+Financials!I31 -> 0 | I14: =+Financials!J31 -> 0 | J14: =+Financials!K31 -> 0 | ... L14: =+Financials!M31 -> 0
B15: Operating Margin | C15: =+Financials!D39 -> #DIV/0! | D15: =+Financials!E39 -> #DIV/0! | E15: =+Financials!F39 -> #DIV/0! | F15: =+Financials!G39 -> #DIV/0! | G15: =+Financials!H39 -> #DIV/0! | H15: =+Financials!I39 -> #DIV/0! | I15: =+Financials!J39 -> #DIV/0! | J15: =+Financials!K39 -> #DIV/0! | ... L15: =+Financials!M39 -> #DIV/0!

Sheet Call-out
C2: =Financials!D116 -> 2016 | D2: =Financials!E116 -> 2017 | E2: =Financials!F116 -> 2018 | F2: =Financials!G116 -> 2019 | G2: =Financials!H116 -> 2020 | H2: =Financials!I116 -> 2021 | I2: =Financials!J116 -> 2022 | J2: =Financials!K116 -> 2023 | ... L2: =Financials!M116 -> 2025
B3: ROIC | C3: =Financials!D133 -> #DIV/0! | D3: =Financials!E133 -> #DIV/0! | E3: =Financials!F133 -> #DIV/0! | F3: =Financials!G133 -> #DIV/0! | G3: =Financials!H133 -> #DIV/0! | H3: =Financials!I133 -> #DIV/0! | I3: =Financials!J133 -> #DIV/0! | J3: =Financials!K133 -> #DIV/0! | ... L3: =Financials!M133 -> #DIV/0!
C5: =Financials!D116 -> 2016 | D5: =Financials!E116 -> 2017 | E5: =Financials!F116 -> 2018 | F5: =Financials!G116 -> 2019 | G5: =Financials!H116 -> 2020 | H5: =Financials!I116 -> 2021 | I5: =Financials!J116 -> 2022 | J5: =Financials!K116 -> 2023 | ... L5: =Financials!M116 -> 2025
B6: ROIC | C6: =C3 -> #DIV/0! | D6: =D3 -> #DIV/0! | E6: =E3 -> #DIV/0! | F6: =F3 -> #DIV/0! | G6: =G3 -> #DIV/0! | H6: =H3 -> #DIV/0! | I6: =I3 -> #DIV/0! | J6: =J3 -> #DIV/0! | ... L6: =L3 -> #DIV/0!
B7: Cost of Capital | C7: 0.1 | D7: =Financials!E134 -> 0.1 | E7: =Financials!F134 -> 0.1 | F7: =Financials!G134 -> 0.1 | G7: =Financials!H134 -> 0.1 | H7: =Financials!I134 -> 0.1 | I7: =Financials!J134 -> 0.1 | J7: =Financials!K134 -> 0.1 | K7: =Financials!L134 -> 0.1 | L7: 0.1
C9: =+C2 -> 2016 | D9: =+D2 -> 2017 | E9: =+E2 -> 2018 | F9: =+F2 -> 2019 | G9: =+G2 -> 2020 | H9: =+H2 -> 2021 | I9: =+I2 -> 2022 | J9: =+J2 -> 2023 | ... L9: =+L2 -> 2025
B10: % margin | C10: =+Financials!D124 -> #DIV/0! | D10: =+Financials!E124 -> #DIV/0! | E10: =+Financials!F124 -> #DIV/0! | F10: =+Financials!G124 -> #DIV/0! | G10: =+Financials!H124 -> #DIV/0! | H10: =+Financials!I124 -> #DIV/0! | I10: =+Financials!J124 -> #DIV/0! | J10: =+Financials!K124 -> #DIV/0! | ... L10: =+Financials!M124 -> #DIV/0!
B11: Scale | C11: =+Financials!D131 -> #DIV/0! | D11: =+Financials!E131 -> #DIV/0! | E11: =+Financials!F131 -> #DIV/0! | F11: =+Financials!G131 -> #DIV/0! | G11: =+Financials!H131 -> #DIV/0! | H11: =+Financials!I131 -> #DIV/0! | I11: =+Financials!J131 -> #DIV/0! | J11: =+Financials!K131 -> #DIV/0! | ... L11: =+Financials!M131 -> #DIV/0!
B12: ROIC | C12: =+C10*C11 -> #DIV/0! | D12: =+D10*D11 -> #DIV/0! | E12: =+E10*E11 -> #DIV/0! | F12: =+F10*F11 -> #DIV/0! | G12: =+G10*G11 -> #DIV/0! | H12: =+H10*H11 -> #DIV/0! | I12: =+I10*I11 -> #DIV/0! | J12: =+J10*J11 -> #DIV/0! | ... L12: =+L10*L11 -> #DIV/0!
C14: =C5 -> 2016 | D14: =D5 -> 2017 | E14: =E5 -> 2018 | F14: =F5 -> 2019 | G14: =G5 -> 2020 | H14: =H5 -> 2021 | I14: =I5 -> 2022 | J14: 2022 | K14: 2023 | L14: =+L2 -> 2025
B15: SHAK - scale | C15: =Financials!D131 -> #DIV/0! | D15: =Financials!E131 -> #DIV/0! | E15: =Financials!F131 -> #DIV/0! | F15: =Financials!G131 -> #DIV/0! | G15: =Financials!H131 -> #DIV/0! | H15: =Financials!I131 -> #DIV/0! | I15: =Financials!J131 -> #DIV/0! | J15: =Financials!K131 -> #DIV/0! | ... L15: =Financials!M131 -> #DIV/0!
B16: CMG - scale | C16: 2.5692396 | D16: 2.5285299 | E16: 2.7227111 | F16: 2.7894053 | G16: 1.2784167 | H16: 1.2091398 | I16: 1.3987815 | J16: 1.5677971 | K16: 1.56
B17: MCD - scale
B19: SHAK - operating margin
B20: CMG operating margin
B21: MCD - operating margin | C21: 0.28941487 | D21: 0.31758661 | E21: 0.36763159 | F21: 0.40607962 | G21: 0.4189212 | H21: 0.38130343 | I21: 0.44593914
